nowcasting_forecast/__init__.py
nowcasting_forecast/app.py
nowcasting_forecast/batch.py
nowcasting_forecast/dataloader.py
nowcasting_forecast/utils.py
nowcasting_forecast/models/__init__.py
nowcasting_forecast/models/hub.py
nowcasting_forecast/models/nwp_solar_simple.py
nowcasting_forecast/models/sun.py
nowcasting_forecast/models/utils.py
nowcasting_forecast-1.3.26.dist-info/LICENSE
nowcasting_forecast-1.3.26.dist-info/METADATA
nowcasting_forecast-1.3.26.dist-info/WHEEL
nowcasting_forecast-1.3.26.dist-info/top_level.txt
nowcasting_forecast-1.3.26.dist-info/RECORD
