Metadata-Version: 2.1
Name: nowcasting-forecast
Version: 1.3.26
Summary: Live forecast for the OCF nowcasting project
Home-page: https://github.com/openclimatefix/nowcasting_forecast
Author: Peter Dudfield
Author-email: peter@openclimatefix.org
License: MIT
Keywords: artificial intelligence,forecast
License-File: LICENSE
Requires-Dist: pydantic
Requires-Dist: sqlalchemy
Requires-Dist: psycopg2-binary
Requires-Dist: numpy
Requires-Dist: click
Requires-Dist: nowcasting-datamodel ==1.5.10
Requires-Dist: pandas ==1.5.3
Requires-Dist: nowcasting-dataset ==3.8.2
Requires-Dist: nowcasting-dataloader ==2.0.5
Requires-Dist: fsspec
Requires-Dist: ocf-blosc2
Requires-Dist: s3fs
Requires-Dist: torch
Requires-Dist: pytorch-lightning <1.9
Requires-Dist: xarray
Requires-Dist: zarr
Requires-Dist: huggingface-hub ==0.4.0
Requires-Dist: pvlib
Requires-Dist: protobuf <4.21.0
Requires-Dist: pathy ==0.6.0
Requires-Dist: testcontainers
